pytorchyolo/__init__.py
pytorchyolo/detect.py
pytorchyolo/models.py
pytorchyolo/test.py
pytorchyolo/train.py
pytorchyolo/utils/__init__.py
pytorchyolo/utils/augmentations.py
pytorchyolo/utils/datasets.py
pytorchyolo/utils/logger.py
pytorchyolo/utils/loss.py
pytorchyolo/utils/parse_config.py
pytorchyolo/utils/transforms.py
pytorchyolo/utils/utils.py
pytorchyolo-1.8.0.dist-info/LICENSE
pytorchyolo-1.8.0.dist-info/METADATA
pytorchyolo-1.8.0.dist-info/WHEEL
pytorchyolo-1.8.0.dist-info/entry_points.txt
pytorchyolo-1.8.0.dist-info/RECORD
