Metadata-Version: 2.1
Name: pytorchyolo
Version: 1.8.0
Summary: Minimal PyTorch implementation of YOLO
Home-page: https://github.com/eriklindernoren/PyTorch-YOLOv3
License: GPL-3.0
Author: Florian Vahl
Author-email: git@flova.de
Requires-Python: >=3.8,<4.0
Classifier: License :: OSI Approved :: GNU General Public License v3 (GPLv3)
Classifier: Programming Language :: Python :: 3
Classifier: Programming Language :: Python :: 3.8
Classifier: Programming Language :: Python :: 3.9
Classifier: Programming Language :: Python :: 3.10
Classifier: Programming Language :: Python :: 3.11
Requires-Dist: Pillow (>=9.1.0,<10.0.0)
Requires-Dist: imgaug (>=0.4.0,<0.5.0)
Requires-Dist: matplotlib (>=3.3.3,<4.0.0)
Requires-Dist: numpy (>=1.23.4,<2.0.0)
Requires-Dist: scipy (<=1.6) ; python_version >= "3.8" and python_version < "3.9"
Requires-Dist: scipy (>=1.9,<2.0) ; python_version >= "3.9" and python_version < "4.0"
Requires-Dist: tensorboard (>=2.10.0,<3.0.0)
Requires-Dist: terminaltables (>=3.1.0,<4.0.0)
Requires-Dist: torch (>=1.10.1,<1.13.0)
Requires-Dist: torchsummary (>=1.5.1,<2.0.0)
Requires-Dist: torchvision (>=0.13.1)
Requires-Dist: tqdm (>=4.64.1,<5.0.0)
Requires-Dist: urllib3 (<=1.22) ; python_version >= "3.8" and python_version < "3.9"
Requires-Dist: urllib3 (>=1.23,<2.0) ; python_version >= "3.9"
Project-URL: Repository, https://github.com/eriklindernoren/PyTorch-YOLOv3
